{
	"playerStart":{
		"x" : 140,
		"y" : 530
	},
	"allPlatformData":[
      {"x" : 130, "y" : 150},
      {"x" : 130, "y" : 250},
      {"x" : 130, "y" : 350},
      {"x" : 130, "y" : 450},
      {"x" : -190, "y" : 480}                                                       
    ],
  "ladders":[
      {"x" : 320, "y" : 195},
      {"x" : 245, "y" : 295},
      {"x" : 320, "y" : 395},
      {"x" : 245, "y" : 500}                                                            
    ],
    "alphabets": [
      {
        "image" : "box_alif",
        "name" : "Alif",
        "x" : 280,
        "y" : 2750
      },
      {
        "image" : "box_baa",
        "name" : "Baa",
        "x" : 180,
        "y" : 2650
      },
      {
        "image" : "box_taa",
        "name" : "Taa",
        "x" : 100,
        "y" : 2550
      },
      {
        "image" : "box_thaa",
        "name" : "Thaa",
        "x" : 100,
        "y" : 2450
      },
      {
        "image" : "box_jim",
        "name" : "Jim",
        "x" : 100,
        "y" : 2350
      },
      {
        "image" : "box_hah",
        "name" : "Hah",
        "x" : 100,
        "y" : 2250
      },
      {
        "image" : "box_kha",
        "name" : "Kha",
        "x" : 100,
        "y" : 2150
      },
      {
        "image" : "box_dal",
        "name" : "Dal",
        "x" : 100,
        "y" : 2050
      },
      {
        "image" : "box_dhal",
        "name" : "Dhal",
        "x" : 100,
        "y" : 1950
      },
      {
        "image" : "box_ra",
        "name" : "Ra",
        "x" : 100,
        "y" : 1850
      },
      {
        "image" : "box_zayin",
        "name" : "Zayin",
        "x" : 100,
        "y" : 1750
      },
      {
        "image" : "box_sin",
        "name" : "Sin",
        "x" : 100,
        "y" : 1650
      },
      {
        "image" : "box_shin",
        "name" : "Shin",
        "x" : 100,
        "y" : 1550
      },
      {
        "image" : "box_sad",
        "name" : "Sad",
        "x" : 100,
        "y" : 1450
      },
      {
        "image" : "box_dad",
        "name" : "Dad",
        "x" : 100,
        "y" : 1350
      },
      {
        "image" : "box_ta",
        "name" : "Ta",
        "x" : 100,
        "y" : 1250
      },
      {
        "image" : "box_za",
        "name" : "Za",
        "x" : 100,
        "y" : 1150
      },
      {
        "image" : "box_ayn",
        "name" : "Ayn",
        "x" : 100,
        "y" : 1050
      },
      {
        "image" : "box_ghain",
        "name" : "Ghain",
        "x" : 100,
        "y" : 950
      },
      {
        "image" : "box_fa",
        "name" : "Fa",
        "x" : 100,
        "y" : 850
      },
      {
        "image" : "box_qaf",
        "name" : "Qaf",
        "x" : 100,
        "y" : 750
      },
      {
        "image" : "box_kaf",
        "name" : "Kaf",
        "x" : 100,
        "y" : 650
      },
      {
        "image" : "box_lam",
        "name" : "Lam",
        "x" : 100,
        "y" : 550
      },
      {
        "image" : "box_mim",
        "name" : "Mim",
        "x" : 100,
        "y" : 450
      },
      {
        "image" : "box_nun",
        "name" : "Nun",
        "x" : 100,
        "y" : 350
      },
      {
        "image" : "box_waw",
        "name" : "Waw",
        "x" : 100,
        "y" : 250
      },
      {
        "image" : "box_ha",
        "name" : "Ha",
        "x" : 100,
        "y" : 150
      },
            {
        "image" : "box_yaa",
        "name" : "Yaa",
        "x" : 280,
        "y" : 50
      }
    ]
}